README.rst
phplist.py
setup.py
phplist_client.egg-info/PKG-INFO
phplist_client.egg-info/SOURCES.txt
phplist_client.egg-info/dependency_links.txt
phplist_client.egg-info/requires.txt
phplist_client.egg-info/top_level.txt