Metadata-Version: 1.1
Name: phplist-client
Version: 1.0.2
Summary: Python client for the phplist REST API
Home-page: https://github.com/tubaman/phplist-restapi-python
Author: Ryan Nowakowski
Author-email: tubaman@fattuba.com
License: Apache 2.0
Keywords: phplist rest client
Platform: UNKNOWN
Classifier: Development Status :: 4 - Beta
Classifier: Intended Audience :: Developers
Classifier: License :: OSI Approved :: Apache Software License
Classifier: Programming Language :: Python :: 3
Classifier: Programming Language :: Python :: 3.5
